anmvc/__init__.py
anmvc/cli.py
anmvc/core.py
anmvc/environment.py
anmvc/storage.py
anmvc-0.0.1.dist-info/METADATA
anmvc-0.0.1.dist-info/WHEEL
anmvc-0.0.1.dist-info/entry_points.txt
anmvc-0.0.1.dist-info/top_level.txt
anmvc-0.0.1.dist-info/RECORD
