Metadata-Version: 2.4
Name: anmvc
Version: 0.0.1
Summary: Automated Asynchronous Native Virtual Containers
Author: KyfStore/KyfStore11k
Author-email: support@kyfstore.com
Requires-Python: >=3.13
Requires-Dist: aiofiles
Requires-Dist: loguru
Requires-Dist: lark
Requires-Dist: prompt_toolkit
Requires-Dist: click
Provides-Extra: dev
Requires-Dist: pytest; extra == "dev"
Requires-Dist: pytest-asyncio; extra == "dev"
